mfast_decoder/__init__.py
mfast_decoder/_core.cpython-39-x86_64-linux-gnu.so
mfast_decoder/mfast_decoder.py
mfast_decoder/bin/fast_type_gen
mfast_decoder/bin/fast_type_gen-1.3.0
mfast_decoder/include/mfast.h
mfast_decoder/include/mfast/aggregate_ref.h
mfast_decoder/include/mfast/allocator.h
mfast_decoder/include/mfast/arena_allocator.h
mfast_decoder/include/mfast/array_view.h
mfast_decoder/include/mfast/boolean_ref.h
mfast_decoder/include/mfast/composite_type.h
mfast_decoder/include/mfast/decimal_ref.h
mfast_decoder/include/mfast/enum_ref.h
mfast_decoder/include/mfast/exceptions.h
mfast_decoder/include/mfast/ext_ref.h
mfast_decoder/include/mfast/field_comparator.h
mfast_decoder/include/mfast/field_instructions.h
mfast_decoder/include/mfast/field_mref.h
mfast_decoder/include/mfast/field_ref.h
mfast_decoder/include/mfast/field_visitor.h
mfast_decoder/include/mfast/group_ref.h
mfast_decoder/include/mfast/int_ref.h
mfast_decoder/include/mfast/malloc_allocator.h
mfast_decoder/include/mfast/message_ref.h
mfast_decoder/include/mfast/mfast_export.h
mfast_decoder/include/mfast/nested_message_ref.h
mfast_decoder/include/mfast/output.h
mfast_decoder/include/mfast/sequence_ref.h
mfast_decoder/include/mfast/sequence_type.h
mfast_decoder/include/mfast/string_ref.h
mfast_decoder/include/mfast/type_category.h
mfast_decoder/include/mfast/value_storage.h
mfast_decoder/include/mfast/vector_ref.h
mfast_decoder/include/mfast/view_iterator.h
mfast_decoder/include/mfast/coder/fast_decoder.h
mfast_decoder/include/mfast/coder/fast_decoder_v2.h
mfast_decoder/include/mfast/coder/fast_encoder.h
mfast_decoder/include/mfast/coder/fast_encoder_v2.h
mfast_decoder/include/mfast/coder/mfast_coder_export.h
mfast_decoder/include/mfast/coder/common/codec_helper.h
mfast_decoder/include/mfast/coder/common/debug_stream.h
mfast_decoder/include/mfast/coder/common/dictionary_builder.h
mfast_decoder/include/mfast/coder/common/exceptions.h
mfast_decoder/include/mfast/coder/common/template_repo.h
mfast_decoder-0.0.3.dist-info/METADATA
mfast_decoder-0.0.3.dist-info/WHEEL
mfast_decoder-0.0.3.dist-info/top_level.txt
mfast_decoder-0.0.3.dist-info/RECORD
