Metadata-Version: 2.1
Name: mfast-decoder
Version: 0.0.3
Summary: MFast python binding(only decode)
Author: Object Computing
License: BSD-V3
Platform: UNKNOWN
Requires-Python: >=3.7
Provides-Extra: test
Requires-Dist: pytest ; extra == 'test'
